{
  "$schema": "https://ui.shadcn.com/schema/registry-item.json",
  "name": "seperateawaydemo",
  "type": "registry:example",
  "title": "seperateawaydemo",
  "description": "Example showing a seperateawaydemo component.",
  "registryDependencies": [
    "https://eldoraui.site/r/seperateaway"
  ],
  "files": [
    {
      "path": "registry/demos/seperateaway-demo.tsx",
      "content": "\"use client\";\n\nimport { SeparateAway } from \"@/components/eldoraui/seperateaway\";\n\nexport default function ScrollBasedVelocityDemo() {\n  return (\n    <SeparateAway\n      className=\"font-display text-center text-4xl font-bold -tracking-widest  text-black dark:text-white md:text-7xl md:leading-[5rem]\"\n      textLeft=\"Seperate\"\n      textRight=\"Away\"\n    />\n  );\n}\n",
      "type": "registry:example",
      "target": "components/seperateaway-demo.tsx"
    }
  ]
}