{
  "$schema": "https://ui.shadcn.com/schema/registry-item.json",
  "name": "dock-text-demo-2",
  "title": "dock-text-demo-2",
  "description": "Example showing a dock-text component with down prop.",
  "registryDependencies": [
    "@eldoraui/dock-text"
  ],
  "files": [
    {
      "path": "registry/example/dock-text-demo-2.tsx",
      "content": "\"use client\"\n\nimport DockText from \"@/registry/eldoraui/dock-text\"\n\nexport default function DockTextDemo2() {\n  return <DockText text={\"Dock Text\"} down={true} />\n}\n",
      "type": "registry:example"
    }
  ],
  "type": "registry:example"
}